{"cameraMode":{"drawMode":0,"name":"Shaded","section":"Shading Mode"},"sceneLighting":true,"audioPlay":false,"sceneViewState":{"m_AlwaysRefresh":false,"showFog":true,"showSkybox":true,"showFlares":true,"showImageEffects":true,"showParticleSystems":true,"showVisualEffectGraphs":true,"m_FxEnabled":true},"in2DMode":false,"pivot":{"x":-5.177122116088867,"y":-6.300418853759766,"z":-2.518564224243164},"rotation":{"x":0.19524793326854707,"y":-0.8005161881446838,"z":0.44399750232696535,"w":0.3520253598690033},"size":38.239051818847659,"orthographic":false}